zmp_openapi_mcp_server/__init__.py
zmp_openapi_mcp_server/__main__.py
zmp_openapi_mcp_server/openapi_mcp_server.py
zmp_openapi_mcp_server/runner/cli.py
zmp_openapi_mcp_server/runner/container.py
zmp_openapi_mcp_server/setting.py
zmp_openapi_mcp_server/tool_spec_manager.py
zmp_openapi_mcp_server-0.2.0.dist-info/METADATA
zmp_openapi_mcp_server-0.2.0.dist-info/WHEEL
zmp_openapi_mcp_server-0.2.0.dist-info/entry_points.txt
zmp_openapi_mcp_server-0.2.0.dist-info/RECORD
