Metadata-Version: 2.3
Name: zmp-openapi-mcp-server
Version: 0.2.0
Summary: This is a mcp server generated automatically using the configured openapi specification
Author: Kilsoo Kang
Author-email: kilsoo75@gmail.com
Requires-Python: >=3.11,<4.0
Classifier: Programming Language :: Python :: 3
Classifier: Programming Language :: Python :: 3.11
Classifier: Programming Language :: Python :: 3.12
Classifier: Programming Language :: Python :: 3.13
Requires-Dist: click (>=8.1.8,<9.0.0)
Requires-Dist: mcp (>=1.6.0,<2.0.0)
Requires-Dist: pydantic (>=2.10.6)
Requires-Dist: python-dotenv (>=1.0.1,<2.0.0)
Requires-Dist: zmp-openapi-helper (>=0.2.0,<0.3.0)
Project-URL: Bug Tracker, https://github.com/cloudz-mp/zmp-openapi-mcp-server/issues
Project-URL: Documentation, https://github.com/cloudz-mp/zmp-openapi-mcp-server
Project-URL: Homepage, https://github.com/cloudz-mp
Project-URL: Repository, https://github.com/cloudz-mp/zmp-openapi-mcp-server
